loguru_feishu_handler/__init__.py
loguru_feishu_handler/handler.py
loguru_feishu_handler-2.0.3.dist-info/licenses/LICENSE
loguru_feishu_handler-2.0.3.dist-info/METADATA
loguru_feishu_handler-2.0.3.dist-info/WHEEL
loguru_feishu_handler-2.0.3.dist-info/top_level.txt
loguru_feishu_handler-2.0.3.dist-info/RECORD
