Metadata-Version: 2.4
Name: loguru-feishu-handler
Version: 2.0.3
Summary: Loguru 飞书消息推送 Handler
Home-page: https://github.com/wersling/loguru_feishu_handler
Author: seanzou
Author-email: wersling@gmail.com
Project-URL: Bug Reports, https://github.com/wersling/loguru_feishu_handler/issues
Project-URL: Source, https://github.com/wersling/loguru_feishu_handler
Keywords: loguru feishu logging handler webhook
Classifier: Development Status :: 4 - Beta
Classifier: Intended Audience :: Developers
Classifier: License :: OSI Approved :: Apache Software License
Classifier: Operating System :: OS Independent
Classifier: Programming Language :: Python :: 3
Classifier: Programming Language :: Python :: 3.7
Classifier: Programming Language :: Python :: 3.8
Classifier: Programming Language :: Python :: 3.9
Classifier: Programming Language :: Python :: 3.10
Classifier: Programming Language :: Python :: 3.11
Classifier: Topic :: System :: Logging
Classifier: Topic :: Software Development :: Libraries :: Python Modules
Requires-Python: >=3.7
License-File: LICENSE
Requires-Dist: loguru>=0.6.0
Requires-Dist: requests>=2.20.0
Dynamic: author
Dynamic: author-email
Dynamic: classifier
Dynamic: description
Dynamic: description-content-type
Dynamic: home-page
Dynamic: keywords
Dynamic: license-file
Dynamic: project-url
Dynamic: requires-dist
Dynamic: requires-python
Dynamic: summary
